lrucli/__init__.py
lrucli/__main__.py
lrucli-2020.8.22.3.dist-info/LICENSE
lrucli-2020.8.22.3.dist-info/METADATA
lrucli-2020.8.22.3.dist-info/WHEEL
lrucli-2020.8.22.3.dist-info/entry_points.txt
lrucli-2020.8.22.3.dist-info/top_level.txt
lrucli-2020.8.22.3.dist-info/zip-safe
lrucli-2020.8.22.3.dist-info/RECORD
